datasette_secret_santa/__init__.py
datasette_secret_santa/words.txt
datasette_secret_santa/templates/_secret_santa_base.html
datasette_secret_santa/templates/index.html
datasette_secret_santa/templates/santa_reveal.html
datasette_secret_santa/templates/santa_set_password.html
datasette_secret_santa/templates/secret_santa.html
datasette_secret_santa/templates/secret_santa_error.html
datasette_secret_santa-0.1.dist-info/LICENSE
datasette_secret_santa-0.1.dist-info/METADATA
datasette_secret_santa-0.1.dist-info/WHEEL
datasette_secret_santa-0.1.dist-info/entry_points.txt
datasette_secret_santa-0.1.dist-info/top_level.txt
datasette_secret_santa-0.1.dist-info/RECORD
