Metadata-Version: 2.1
Name: datasette-secret-santa
Version: 0.1
Summary: Run a secret santa using Datasette
Home-page: https://github.com/simonw/datasette-secret-santa
Author: Simon Willison
License: Apache License, Version 2.0
Project-URL: Issues, https://github.com/simonw/datasette-secret-santa/issues
Project-URL: CI, https://github.com/simonw/datasette-secret-santa/actions
Project-URL: Changelog, https://github.com/simonw/datasette-secret-santa/releases
Classifier: Framework :: Datasette
Classifier: License :: OSI Approved :: Apache Software License
Requires-Python: >=3.7
License-File: LICENSE
Requires-Dist: datasette
Requires-Dist: cryptography
Provides-Extra: test
Requires-Dist: pytest ; extra == 'test'
Requires-Dist: pytest-asyncio ; extra == 'test'
